MANIFEST.in
README.md
setup.py
django_drole.egg-info/PKG-INFO
django_drole.egg-info/SOURCES.txt
django_drole.egg-info/dependency_links.txt
django_drole.egg-info/namespace_packages.txt
django_drole.egg-info/not-zip-safe
django_drole.egg-info/requires.txt
django_drole.egg-info/top_level.txt
drole/__init__.py
drole/fields.py
drole/models.py
drole/test_models.py
drole/types.py
drole/tests/__init__.py
drole/tests/test_authentication.py
drole/tests/test_fields.py
drole/tests/test_permission.py
drole/tests/test_roles.py