Metadata-Version: 1.1
Name: django-drole
Version: 0.1.0
Summary: Django Drole: Zope/Plone inspired roles/permissions
Home-page: http://github.com/iivvoo/django_drole
Author: Ivo van der Wijk
Author-email: two@in.m3r.nl
License: BSD
Platform: UNKNOWN
Classifier: Programming Language :: Python
